{
"type": "FeatureCollection",
"name": "oleholeh",
"crs": { "type": "name", "properties": { "name": "urn:ogc:def:crs:OGC:1.3:CRS84" } },
"features": [
{ "type": "Feature", "properties": { "Id": null, "Oleh-oleh": "Coklat Monggo" }, "geometry": { "type": "Point", "coordinates": [ 110.399646102572007, -7.831718824256931 ] } },
{ "type": "Feature", "properties": { "Id": null, "Oleh-oleh": "Dagadu Djogdja Keraton" }, "geometry": { "type": "Point", "coordinates": [ 110.365766670417372, -7.803232721236043 ] } },
{ "type": "Feature", "properties": { "Id": null, "Oleh-oleh": "Dagadu Djogdja-Malioboro Mall" }, "geometry": { "type": "Point", "coordinates": [ 110.366147990234154, -7.792951032875242 ] } },
{ "type": "Feature", "properties": { "Id": null, "Oleh-oleh": "Dagadu Djogdja-Janti" }, "geometry": { "type": "Point", "coordinates": [ 110.402413747838054, -7.802457305957715 ] } },
{ "type": "Feature", "properties": { "Id": null, "Oleh-oleh": "Hamzah Batik" }, "geometry": { "type": "Point", "coordinates": [ 110.364750909474267, -7.799171202319934 ] } },
{ "type": "Feature", "properties": { "Id": null, "Oleh-oleh": "Sentra Bakpia" }, "geometry": { "type": "Point", "coordinates": [ 110.359822843102918, -7.797548325196916 ] } },
{ "type": "Feature", "properties": { "Id": null, "Oleh-oleh": "Sentra Batik" }, "geometry": { "type": "Point", "coordinates": [ 110.370865282590131, -7.819192337455655 ] } },
{ "type": "Feature", "properties": { "Id": null, "Oleh-oleh": "Gudeg Wijilan" }, "geometry": { "type": "Point", "coordinates": [ 110.366579236006842, -7.804145669830182 ] } },
{ "type": "Feature", "properties": { "Id": null, "Oleh-oleh": "Sentra Yangko" }, "geometry": { "type": "Point", "coordinates": [ 110.399250779422786, -7.830963606026561 ] } },
{ "type": "Feature", "properties": { "Id": null, "Oleh-oleh": "Pasar Klithikan" }, "geometry": { "type": "Point", "coordinates": [ 110.353292525982894, -7.797271535728796 ] } },
{ "type": "Feature", "properties": { "Id": null, "Oleh-oleh": "Suvenir Kerajinan Perak Kotagede" }, "geometry": { "type": "Point", "coordinates": [ 110.399776959690897, -7.825495679714884 ] } },
{ "type": "Feature", "properties": { "Id": null, "Oleh-oleh": "Teras Malioboro" }, "geometry": { "type": "Point", "coordinates": [ 110.364574110355989, -7.798770445428615 ] } }
]
}
